denmune/__init__.py
denmune/denmune.py
denmune/functions.py
abbas_ml-0.0.0.0.dist-info/LICENSE
abbas_ml-0.0.0.0.dist-info/METADATA
abbas_ml-0.0.0.0.dist-info/WHEEL
abbas_ml-0.0.0.0.dist-info/top_level.txt
abbas_ml-0.0.0.0.dist-info/RECORD
