Metadata-Version: 2.1
Name: abbas-ml
Version: 0.0.0.0
Summary: This is the package for DenMune Clustering Algorithm published in paper https://doi.org/10.1016/j.patcog.2020.107589
Home-page: https://github.com/pypa/sampleproject
Author: Mohamed Ali Abbas
Author-email: mohamed.alyabbas@outlook.com
License: UNKNOWN
Project-URL: Bug Tracker, https://github.com/pypa/sampleproject/issues
Platform: UNKNOWN
Classifier: Programming Language :: Python :: 3
Classifier: License :: OSI Approved :: MIT License
Classifier: Operating System :: OS Independent
Requires-Python: >=3.6
License-File: LICENSE
